_ukkonen.abi3.so
ukkonen.py
ukkonen-1.1.0.dist-info/licenses/LICENSE
ukkonen-1.1.0.dist-info/licenses/licenses/LICENSE
ukkonen-1.1.0.dist-info/METADATA
ukkonen-1.1.0.dist-info/WHEEL
ukkonen-1.1.0.dist-info/top_level.txt
ukkonen-1.1.0.dist-info/RECORD
