Metadata-Version: 2.4
Name: ukkonen
Version: 1.1.0
Summary: Implementation of bounded Levenshtein distance (Ukkonen)
Home-page: https://www.github.com/asottile/ukkonen
Author: Anthony Sottile
Author-email: asottile@umich.edu
License: MIT
Classifier: Programming Language :: Python :: 3
Classifier: Programming Language :: Python :: 3 :: Only
Classifier: Programming Language :: Python :: Implementation :: CPython
Classifier: Programming Language :: Python :: Implementation :: PyPy
Requires-Python: >=3.10
License-File: LICENSE
License-File: licenses/LICENSE
Requires-Dist: cffi>=1
Dynamic: license-file
